underthesea_core/__init__.py
underthesea_core/underthesea_core.cpython-310-darwin.so
underthesea_core-3.0.5.dist-info/METADATA
underthesea_core-3.0.5.dist-info/WHEEL
underthesea_core-3.0.5.dist-info/RECORD
