Metadata-Version: 2.4
Name: underthesea_core
Version: 3.0.5
Classifier: Programming Language :: Rust
Classifier: Programming Language :: Python :: Implementation :: CPython
Classifier: Programming Language :: Python :: 3.10
Classifier: Programming Language :: Python :: 3.11
Classifier: Programming Language :: Python :: 3.12
Classifier: Programming Language :: Python :: 3.13
Classifier: Programming Language :: Python :: 3.14
Summary: Underthesea Core
Home-Page: https://github.com/undertheseanlp/underthesea/tree/main/extensions/underthesea_core
Author-email: Vu Anh <anhv.ict91@gmail.com>
License: GPL-3.0
Requires-Python: >=3.10
Project-URL: Homepage, https://github.com/undertheseanlp/underthesea/tree/main/extensions/underthesea_core
Project-URL: Repository, https://github.com/undertheseanlp/underthesea/
